latin/__init__.py
latin/a_colat1.py
latin/a_colat2.py
latin/a_colat3.py
latin/a_colat4.py
latin/a_global.py
latin/add_path.py
latin/bglobals.py
latin/c_colat1.py
latin/c_colat2.py
latin/c_colat3.py
latin/c_colat4.py
latin/e_pedocerto.py
latin/gglobal.py
latin/h_fact_organizer.py
latin/i_scrape_old.py
latin/j_lasla.py
latin/j_lasla2.py
latin/k_macr_txt.py
latin/lglobals.py
latin/m_stems.py
latin/o_memorize.py
latin/v_reading.py
latin/w_convert_mod.py
latin/z_begin.py
latin/general_la/__init__.py
latin/general_la/abbreviations.py
latin/general_la/pickling.py
latin/general_la/trans_obj.py
latin/general_la/very_general_functions.py
latin_databases-0.1.5.dist-info/METADATA
latin_databases-0.1.5.dist-info/WHEEL
latin_databases-0.1.5.dist-info/top_level.txt
latin_databases-0.1.5.dist-info/RECORD
