Metadata-Version: 2.1
Name: latin-databases
Version: 0.1.5
Summary: none
Home-page: https://github.com/kylefoley76/latin_databases3
Author: Kyle Foley
Author-email: kylefoley202@gmail.com
License: BSD
Classifier: Development Status :: 1 - Planning
Classifier: Intended Audience :: Education
Classifier: License :: OSI Approved :: GNU General Public License (GPL)
Classifier: Operating System :: MacOS
Classifier: Programming Language :: Python :: 3.8
Requires-Dist: Levenshtein
Requires-Dist: striprtf (==0.0.12)
